Metadata-Version: 2.1
Name: trask
Version: 1.2.0
Summary: Declarative recipe-based task runner
Home-page: https://github.com/nicholasbishop/trask
Author: Nicholas Bishop
Author-email: nicholasbishop@gmail.com
License: UNKNOWN
Platform: UNKNOWN
